webdavit/__init__.py
webdavit/client.py
webdavit/exceptions.py
webdavit/py.typed
webdavit/xml_utils.py
webdavit-0.1.0.dist-info/WHEEL
webdavit-0.1.0.dist-info/METADATA
webdavit-0.1.0.dist-info/RECORD
