Metadata-Version: 2.3
Name: webdavit
Version: 0.1.0
Summary: A simple async WebDAV client for Python
Keywords: webdav,async,client,http,aiohttp
Author: merlinz01
Author-email: merlinz01 <158784988+merlinz01@users.noreply.github.com>
License: Copyright (c) 2025 Merlin Zimmerman
Classifier: Programming Language :: Python :: 3.13
Classifier: License :: OSI Approved :: MIT License
Classifier: Operating System :: OS Independent
Classifier: Topic :: Internet :: WWW/HTTP
Classifier: Topic :: Software Development :: Libraries :: Python Modules
Requires-Dist: aiohttp>=3.8.0
Requires-Dist: lxml>=4.9.0
Requires-Python: >=3.12
